reflex_pdf_viewer/__init__.py
reflex_pdf_viewer/pdf_viewer.py
reflex_pdf_viewer-0.0.1.dist-info/METADATA
reflex_pdf_viewer-0.0.1.dist-info/WHEEL
reflex_pdf_viewer-0.0.1.dist-info/top_level.txt
reflex_pdf_viewer-0.0.1.dist-info/RECORD
