Metadata-Version: 2.4
Name: reflex-pdf-viewer
Version: 0.0.1
Summary: Reflex custom component pdf-viewer
Author-email: Tamilselvan K <tamilselvan@codeplugtech.in>
License: Apache-2.0
Project-URL: homepage, https://github.com/codeplugtech/reflex-pdf-viewer
Keywords: reflex,reflex-custom-components
Classifier: Development Status :: 4 - Beta
Requires-Python: >=3.10
Requires-Dist: reflex>=0.8.10
Provides-Extra: dev
Requires-Dist: build; extra == "dev"
Requires-Dist: twine; extra == "dev"
